{
    "swagger": "2.0",
    "info": {
        "description": "电商平台，api接口站的文档内容.",
        "title": "电商接口站文档",
        "termsOfService": "http://swagger.io/terms/",
        "contact": {
            "name": "API Support",
            "url": "http://www.swagger.io/support",
            "email": "371125307@qq.com"
        },
        "license": {
            "name": "Apache 2.0",
            "url": "http://www.apache.org/licenses/LICENSE-2.0.html"
        },
        "version": "1.0"
    },
    "host": "api.estorelhd.com",
    "paths": {}
}